POP/Embedder.py
POP/POP.py
POP/__init__.py
POP/prompts/fabric-improve_prompt.md
POP/prompts/json_formatter_prompt.md
POP/prompts/openai-function_description_generator.md
POP/prompts/openai-json_schema_generator.md
POP/prompts/openai-prompt_generator.md
pop_guotai-0.3.3.dist-info/licenses/LICENSE
pop_guotai-0.3.3.dist-info/METADATA
pop_guotai-0.3.3.dist-info/WHEEL
pop_guotai-0.3.3.dist-info/top_level.txt
pop_guotai-0.3.3.dist-info/RECORD
