Metadata-Version: 2.4
Name: POP-guotai
Version: 0.3.3
Summary: [DEPRECATED] Reusable, mutable, prompt functions for LLMs. Please migrate to the new package: pypop.
Home-page: https://github.com/sgt1796/POP
Author: Guotai Shen
Author-email: sgt1796@gmail.com
Classifier: Development Status :: 7 - Inactive
Classifier: Programming Language :: Python :: 3
Classifier: License :: OSI Approved :: MIT License
Classifier: Operating System :: OS Independent
Requires-Python: >=3.7
License-File: LICENSE
Requires-Dist: openai>=1.0.0
Requires-Dist: requests>=2.25.0
Requires-Dist: python-dotenv
Requires-Dist: pydantic>=1.10
Requires-Dist: transformers>=4.30.0
Requires-Dist: numpy>=1.21
Requires-Dist: backoff
Requires-Dist: Pillow>=9.0
Requires-Dist: google-genai>=0.2.0
Dynamic: author
Dynamic: author-email
Dynamic: classifier
Dynamic: description
Dynamic: description-content-type
Dynamic: home-page
Dynamic: license-file
Dynamic: requires-dist
Dynamic: requires-python
Dynamic: summary
